imgparallel/__init__.py
imgparallel/cli.py
imgparallel-0.1.0.dist-info/LICENSE
imgparallel-0.1.0.dist-info/METADATA
imgparallel-0.1.0.dist-info/WHEEL
imgparallel-0.1.0.dist-info/entry_points.txt
imgparallel-0.1.0.dist-info/top_level.txt
imgparallel-0.1.0.dist-info/RECORD
